Metadata-Version: 2.1
Name: slamdunk
Version: 0.4.0
Summary: SLAMdunk suite for analyzing SLAM-seq data
Home-page: http://t-neumann.github.io/slamdunk
Author: Tobias Neumann, Philipp Rescheneder
Author-email: tobias.neumann.at@gmail.com, philipp.rescheneder@univie.ac.at
License: GNU Affero General Public License v3 or later (AGPLv3+)
Keywords: Next-Generation-Sequencing NGS QuantSeq SLAMSeq
Platform: UNKNOWN
Classifier: Development Status :: 4 - Beta
Classifier: Intended Audience :: Science/Research
Classifier: Topic :: Scientific/Engineering :: Bio-Informatics
Classifier: License :: OSI Approved :: GNU Affero General Public License v3 or later (AGPLv3+)
Classifier: Programming Language :: Python :: 2
Classifier: Programming Language :: Python :: 2.6
Classifier: Programming Language :: Python :: 2.7
Classifier: Programming Language :: Python :: 3
Classifier: Programming Language :: Python :: 3.3
Classifier: Programming Language :: Python :: 3.4
Classifier: Programming Language :: Python :: 3.5
Classifier: Programming Language :: C++
Classifier: Programming Language :: Java
Requires-Dist: joblib (>=0.9.4)
Requires-Dist: pybedtools (>=0.6.4)
Requires-Dist: intervaltree (>=2.1.0)
Requires-Dist: pandas (>=0.13.1)
Requires-Dist: biopython (>=1.63)
Requires-Dist: pysam (>=0.8.3)
Requires-Dist: Cython (>=0.20.1)
